proj_bolt/__init__.py
proj_bolt/bolt_py.py
proj_bolt/ide_launcher/__init__.py
proj_bolt/ide_launcher/launcher.py
proj_bolt/ide_launcher/main.py
proj_bolt/template/__init__.py
proj_bolt/template/base_template.py
proj_bolt/template/licence_template.py
proj_bolt/template/readme_template.py
proj_bolt/template/bolt_py/__init__.py
proj_bolt/template/bolt_py/gitignore_template.py
proj_bolt/template/bolt_py/setuppy_template.py
proj_bolt-0.0.1.2.dist-info/METADATA
proj_bolt-0.0.1.2.dist-info/WHEEL
proj_bolt-0.0.1.2.dist-info/entry_points.txt
proj_bolt-0.0.1.2.dist-info/top_level.txt
proj_bolt-0.0.1.2.dist-info/RECORD
