Metadata-Version: 2.1
Name: proj-bolt
Version: 0.0.1.2
Author: steveflyer
Author-email: steveflyer7@gmail.com
Requires-Dist: twine
